envoy/__init__.py
envoy/accounts.py
envoy/apikeys.py
envoy/auditlogs.py
envoy/client.py
envoy/counterparties.py
envoy/credentials.py
envoy/exceptions.py
envoy/records.py
envoy/resource.py
envoy/transactions.py
envoy/users.py
envoy/utilities.py
envoy/version.py
pyenvoy-1.2.0.dist-info/licenses/LICENSE
pyenvoy-1.2.0.dist-info/METADATA
pyenvoy-1.2.0.dist-info/WHEEL
pyenvoy-1.2.0.dist-info/top_level.txt
pyenvoy-1.2.0.dist-info/zip-safe
pyenvoy-1.2.0.dist-info/RECORD
