Metadata-Version: 2.4
Name: pyenvoy
Version: 1.2.0
Summary: An API client for TRISA Envoy nodes that enables travel rule compliance.
Home-page: https://trisa.dev
Download-URL: https://github.com/trisacrypto/pyenvoy/tarball/v1.2.0
Author: Rotational Labs
Author-email: support@rotational.io
Maintainer: Rotational Labs
Maintainer-email: support@rotational.io
License-Expression: MIT
Project-URL: Documentation, https://trisa.dev
Project-URL: Download, https://github.com/trisacrypto/pyenvoy/tarball/v1.2.0
Project-URL: Source, https://github.com/trisacrypto/pyenvoy
Project-URL: Tracker, https://github.com/trisacrypto/pyenvoy/issues
Keywords: travel rule,trisa,envoy,api client
Classifier: Development Status :: 5 - Production/Stable
Classifier: Intended Audience :: Developers
Classifier: Natural Language :: English
Classifier: Operating System :: OS Independent
Classifier: Programming Language :: Python
Classifier: Programming Language :: Python :: 3.12
Classifier: Topic :: Software Development
Classifier: Topic :: Software Development :: Libraries :: Python Modules
Requires-Python: >=3.10, <4
License-File: LICENSE
Requires-Dist: PyJWT<2.10.0,>=2.9.0
Requires-Dist: python-dotenv<1.2.0,>=1.1.0
Requires-Dist: requests<2.33.0,>=2.32.0
Dynamic: author
Dynamic: author-email
Dynamic: classifier
Dynamic: description
Dynamic: description-content-type
Dynamic: download-url
Dynamic: home-page
Dynamic: keywords
Dynamic: license-file
Dynamic: license-expression
Dynamic: maintainer
Dynamic: maintainer-email
Dynamic: project-url
Dynamic: requires-dist
Dynamic: requires-python
Dynamic: summary
